{
  "verse_reference": "Ezekiel 8:2",
  "version": "ESV",
  "original_text": "Then I looked, and behold, a form that had the appearance of a man. Below what appeared to be his waist was fire, and above his waist was something like the appearance of brightness, like gleaming metal.",
  "korean_text": "내가 보니 불 같은 형상이 있더라 그 허리 아래의 모양은 불 같고 허리 위에는 광채가 나서 단 쇠 같은데",
  "sentences": [
    {
      "sequence_order": 1,
      "original_text": "Then I looked, and behold, a form",
      "korean_translation": "내가 보니, 보라, 한 형상이",
      "word_indices": [
        91,
        527
      ]
    },
    {
      "sequence_order": 2,
      "original_text": "that had the appearance of a man.",
      "korean_translation": "사람의 모양과 같은 것이",
      "word_indices": [
        6,
        617
      ]
    },
    {
      "sequence_order": 3,
      "original_text": "Below what appeared to be his waist was fire,",
      "korean_translation": "허리로 보이는 것 아래는 불이었고",
      "word_indices": [
        72,
        1119
      ]
    },
    {
      "sequence_order": 4,
      "original_text": "and above his waist was something like the appearance of brightness,",
      "korean_translation": "허리 위는 광채 같은 것이 보였는데",
      "word_indices": [
        14,
        617,
        1119
      ]
    },
    {
      "sequence_order": 5,
      "original_text": "like gleaming metal.",
      "korean_translation": "빛나는 쇠 같았더라",
      "word_indices": [
        14,
        1064,
        2837
      ]
    }
  ]
}