{
  "verse_reference": "Ezekiel 24:14",
  "version": "ESV",
  "original_text": "I am the Lord. I have spoken; it shall come to pass; I will do it. I will not go back; I will not spare; I will not relent; according to your ways and your deeds you will be judged, declares the Lord God.”",
  "korean_text": "나 여호와가 말하였은즉 그 일이 이루어질지라 내가 돌이키지도 아니하고 아끼지도 아니하며 뉘우치지도 아니하고 행하리니 그들이 네 모든 행위대로 너를 재판하리라 주 여호와의 말씀이니라",
  "sentences": [
    {
      "sequence_order": 1,
      "original_text": "I am the Lord.",
      "korean_translation": "나는 주이다.",
      "word_indices": []
    },
    {
      "sequence_order": 2,
      "original_text": "I have spoken;",
      "korean_translation": "내가 말하였으니",
      "word_indices": []
    },
    {
      "sequence_order": 3,
      "original_text": "it shall come to pass;",
      "korean_translation": "그것이 이루어질 것이다",
      "word_indices": [
        231
      ]
    },
    {
      "sequence_order": 4,
      "original_text": "I will do it.",
      "korean_translation": "내가 그것을 행하리라",
      "word_indices": []
    },
    {
      "sequence_order": 5,
      "original_text": "I will not go back;",
      "korean_translation": "내가 돌이키지 아니하리라",
      "word_indices": [
        90
      ]
    },
    {
      "sequence_order": 6,
      "original_text": "I will not spare;",
      "korean_translation": "내가 아끼지 아니하리라",
      "word_indices": [
        971
      ]
    },
    {
      "sequence_order": 7,
      "original_text": "I will not relent;",
      "korean_translation": "내가 뉘우치지 아니하리라",
      "word_indices": [
        1287
      ]
    },
    {
      "sequence_order": 8,
      "original_text": "according to your ways and your deeds you will be judged,",
      "korean_translation": "너희의 길과 행위대로 너희가 심판을 받으리라",
      "word_indices": [
        49,
        261
      ]
    },
    {
      "sequence_order": 9,
      "original_text": "declares the Lord God.”",
      "korean_translation": "주 하나님이 말씀하시느니라",
      "word_indices": [
        1
      ]
    }
  ]
}