{
  "verse_reference": "Ezekiel 13:15",
  "version": "ESV",
  "original_text": "Thus will I spend my wrath upon the wall and upon those who have smeared it with whitewash, and I will say to you, The wall is no more, nor those who smeared it,",
  "korean_text": "이와 같이 내가 내 노를 담과 회칠한 자에게 모두 이루고 또 너희에게 말하기를 담도 없어지고 칠한 자들도 없어졌다 하리니",
  "sentences": [
    {
      "sequence_order": 1,
      "original_text": "Thus will I spend my wrath upon the wall",
      "korean_translation": "이와 같이 내가 그 벽에 나의 진노를 쏟으리라",
      "word_indices": [
        191,
        226,
        654
      ]
    },
    {
      "sequence_order": 2,
      "original_text": "and upon those who have smeared it with whitewash",
      "korean_translation": "그것을 흰 칠로 바른 자들에게도",
      "word_indices": [
        1950,
        2441
      ]
    },
    {
      "sequence_order": 3,
      "original_text": "and I will say to you",
      "korean_translation": "그리고 내가 너희에게 이르기를",
      "word_indices": []
    },
    {
      "sequence_order": 4,
      "original_text": "The wall is no more",
      "korean_translation": "그 벽이 더 이상 없고",
      "word_indices": [
        191
      ]
    },
    {
      "sequence_order": 5,
      "original_text": "nor those who smeared it",
      "korean_translation": "그것을 바른 자들도 없어지리라",
      "word_indices": [
        1950
      ]
    }
  ]
}