{
  "verse_reference": "Ezekiel 44:14",
  "version": "ESV",
  "original_text": "Yet I will appoint them to keep charge of the temple, to do all its service and all that is to be done in it.",
  "korean_text": "그러나 내가 그들을 세워 성전을 지키게 하고 성전에 모든 수종드는 일과 그 가운데에서 행하는 모든 일을 맡기리라",
  "sentences": [
    {
      "sequence_order": 1,
      "original_text": "Yet I will appoint them",
      "korean_translation": "그러나 내가 그들을 임명하리니",
      "word_indices": [
        245
      ]
    },
    {
      "sequence_order": 2,
      "original_text": "to keep charge of the temple,",
      "korean_translation": "그들은 성전을 맡아 지키고",
      "word_indices": [
        46,
        170,
        263
      ]
    },
    {
      "sequence_order": 3,
      "original_text": "to do all its service",
      "korean_translation": "그 모든 섬기는 일을 하며",
      "word_indices": [
        327
      ]
    },
    {
      "sequence_order": 4,
      "original_text": "and all that is to be done in it.",
      "korean_translation": "그 안에서 행해야 할 모든 일을 하게 하리라",
      "word_indices": []
    }
  ]
}