{
  "verse_reference": "Luke 5:34",
  "version": "NIV",
  "original_text": "Jesus answered, “Can you make the friends of the bridegroom fast while he is with them?",
  "korean_text": "예수께서 그들에게 이르시되 혼인 집 손님들이 신랑과 함께 있을 때에 너희가 그 손님으로 금식하게 할 수 있느냐",
  "sentences": [
    {
      "sequence_order": 1,
      "original_text": "Jesus answered",
      "korean_translation": "예수께서 대답하셨다",
      "word_indices": [
        63
      ]
    },
    {
      "sequence_order": 2,
      "original_text": "Can you make the friends of the bridegroom fast",
      "korean_translation": "신랑의 친구들을 금식하게 할 수 있느냐",
      "word_indices": [
        335,
        592,
        1426
      ]
    },
    {
      "sequence_order": 3,
      "original_text": "while he is with them",
      "korean_translation": "신랑이 그들과 함께 있는 동안에",
      "word_indices": []
    }
  ]
}