{
  "verse_reference": "Luke 24:3",
  "version": "KJV",
  "original_text": "And they entered in, and found not the body of the Lord Jesus.",
  "korean_text": "들어가니 주 예수의 시체가 보이지 아니하더라",
  "sentences": [
    {
      "sequence_order": 1,
      "original_text": "And they entered in",
      "korean_translation": "그들이 들어가니",
      "word_indices": []
    },
    {
      "sequence_order": 2,
      "original_text": "and found not the body",
      "korean_translation": "몸을 찾지 못하였고",
      "word_indices": [
        152,
        1903
      ]
    },
    {
      "sequence_order": 3,
      "original_text": "of the Lord Jesus",
      "korean_translation": "주 예수의",
      "word_indices": []
    }
  ]
}