{
  "verse_reference": "Romans 4:21",
  "version": "KJV",
  "original_text": "And being fully persuaded that, what he had promised, he was able also to perform.",
  "korean_text": "약속하신 그것을 또한 능히 이루실 줄을 확신하였으니",
  "sentences": [
    {
      "sequence_order": 1,
      "original_text": "And being fully persuaded",
      "korean_translation": "그리고 완전히 확신하여",
      "word_indices": [
        1628
      ]
    },
    {
      "sequence_order": 2,
      "original_text": "that what he had promised",
      "korean_translation": "그가 약속한 것을",
      "word_indices": []
    },
    {
      "sequence_order": 3,
      "original_text": "he was able also to perform",
      "korean_translation": "그가 또한 이행할 수 있음을",
      "word_indices": [
        9,
        209,
        481
      ]
    }
  ]
}