{
  "verse_reference": "Psalms 48:11",
  "version": "NIV",
  "original_text": "Mount Zion rejoices,\n    the villages of Judah are glad\n    because of your judgments.",
  "korean_text": "주의 심판으로 말미암아 시온 산은 기뻐하고 유다의 딸들은 즐거워할지어다",
  "sentences": [
    {
      "sequence_order": 1,
      "original_text": "Mount Zion rejoices",
      "korean_translation": "시온 산이 기뻐하며",
      "word_indices": [
        308
      ]
    },
    {
      "sequence_order": 2,
      "original_text": "the villages of Judah are glad",
      "korean_translation": "유다의 촌락들이 즐거워하나니",
      "word_indices": [
        691
      ]
    },
    {
      "sequence_order": 3,
      "original_text": "because of your judgments",
      "korean_translation": "주의 심판 때문이로다",
      "word_indices": [
        380
      ]
    }
  ]
}