{
  "verse_reference": "Isaiah 51:8",
  "version": "ESV",
  "original_text": "For the moth will eat them up like a garment,\n    and the worm will eat them like wool,\nbut my righteousness will be forever,\n    and my salvation to all generations.”",
  "korean_text": "옷 같이 좀이 그들을 먹을 것이며 양털 같이 좀벌레가 그들을 먹을 것이나 나의 공의는 영원히 있겠고 나의 구원은 세세에 미치리라",
  "sentences": [
    {
      "sequence_order": 1,
      "original_text": "For the moth will eat them up like a garment,",
      "korean_translation": "나방이 그것을 옷처럼 먹어 버릴 것이니,",
      "word_indices": [
        14,
        218,
        2086
      ]
    },
    {
      "sequence_order": 2,
      "original_text": "and the worm will eat them like wool,",
      "korean_translation": "좀벌레가 그것을 양털처럼 갉아 먹을 것이며,",
      "word_indices": [
        14,
        1552,
        1652
      ]
    },
    {
      "sequence_order": 3,
      "original_text": "but my righteousness will be forever,",
      "korean_translation": "나의 의는 영원히 있을 것이나,",
      "word_indices": [
        96
      ]
    },
    {
      "sequence_order": 4,
      "original_text": "and my salvation to all generations.”",
      "korean_translation": "나의 구원은 대대에 미치리라.”",
      "word_indices": [
        225,
        281
      ]
    }
  ]
}