{
  "verse_reference": "Job 32:17",
  "version": "ESV",
  "original_text": "I also will answer with my share;\n    I also will declare my opinion.",
  "korean_text": "나는 내 본분대로 대답하고 나도 내 의견을 보이리라",
  "sentences": [
    {
      "sequence_order": 1,
      "original_text": "I also will answer with my share",
      "korean_translation": "나도 나의 몫으로 대답하겠다",
      "word_indices": [
        23,
        54,
        734
      ]
    },
    {
      "sequence_order": 2,
      "original_text": "I also will declare my opinion.",
      "korean_translation": "나도 나의 의견을 말하겠다",
      "word_indices": [
        23,
        67,
        2297
      ]
    }
  ]
}