{
  "verse_reference": "Daniel 5:14",
  "version": "ESV",
  "original_text": "I have heard of you that the spirit of the gods is in you, and that light and understanding and excellent wisdom are found in you.",
  "korean_text": "내가 네게 대하여 들은즉 네 안에는 신들의 영이 있으므로 네가 명철과 총명과 비상한 지혜가 있다 하도다",
  "sentences": [
    {
      "sequence_order": 1,
      "original_text": "I have heard of you",
      "korean_translation": "나는 당신에 대해 들었습니다",
      "word_indices": []
    },
    {
      "sequence_order": 2,
      "original_text": "that the spirit of the gods is in you",
      "korean_translation": "신들의 영이 당신 안에 있다는 것",
      "word_indices": [
        1,
        55
      ]
    },
    {
      "sequence_order": 3,
      "original_text": "and that light and understanding and excellent wisdom",
      "korean_translation": "그리고 빛과 명철과 탁월한 지혜가",
      "word_indices": [
        177,
        224,
        1633
      ]
    },
    {
      "sequence_order": 4,
      "original_text": "are found in you.",
      "korean_translation": "당신에게서 발견되었다는 것입니다",
      "word_indices": [
        1942
      ]
    }
  ]
}