{
  "verse_reference": "2 Chronicles 19:11",
  "version": "KJV",
  "original_text": "And, behold, Amariah the chief priest is over you in all matters of the Lord; and Zebadiah the son of Ishmael, the ruler of the house of Judah, for all the king's matters: also the Levites shall be officers before you. Deal courageously, and the Lord shall be with the good.",
  "korean_text": "여호와께 속한 모든 일에는 대제사장 아마랴가 너희를 다스리고 왕에게 속한 모든 일은 유다 지파의 어른 이스마엘의 아들 스바댜가 다스리고 레위 사람들은 너희 앞에 관리가 되리라 너희는 힘써 행하라 여호와께서 선한 자와 함께 하실지로다 하니라",
  "sentences": [
    {
      "sequence_order": 1,
      "original_text": "And, behold",
      "korean_translation": "그리고 보라",
      "word_indices": []
    },
    {
      "sequence_order": 2,
      "original_text": "Amariah the chief priest is over you",
      "korean_translation": "대제사장 아마랴가 너희를 다스리나니",
      "word_indices": [
        3,
        18,
        108
      ]
    },
    {
      "sequence_order": 3,
      "original_text": "in all matters of the Lord",
      "korean_translation": "여호와의 모든 일에 있어서",
      "word_indices": [
        320
      ]
    },
    {
      "sequence_order": 4,
      "original_text": "and Zebadiah the son of Ishmael",
      "korean_translation": "그리고 이스마엘의 아들 스바댜가",
      "word_indices": []
    },
    {
      "sequence_order": 5,
      "original_text": "the ruler of the house of Judah",
      "korean_translation": "유다 집의 지도자로서",
      "word_indices": [
        4,
        201
      ]
    },
    {
      "sequence_order": 6,
      "original_text": "for all the king's matters",
      "korean_translation": "왕의 모든 일에 있어서",
      "word_indices": [
        320
      ]
    },
    {
      "sequence_order": 7,
      "original_text": "also the Levites shall be officers before you",
      "korean_translation": "또한 레위 사람들이 너희 앞에 관리로 있으리라",
      "word_indices": [
        3,
        9,
        443
      ]
    },
    {
      "sequence_order": 8,
      "original_text": "Deal courageously",
      "korean_translation": "담대히 행하라",
      "word_indices": [
        4725
      ]
    },
    {
      "sequence_order": 9,
      "original_text": "and the Lord shall be with the good",
      "korean_translation": "그리하면 여호와께서 선한 자와 함께 하시리라",
      "word_indices": []
    }
  ]
}