{
  "verse_reference": "2 Corinthians 2:13",
  "version": "NIV",
  "original_text": "I still had no peace of mind, because I did not find my brother Titus there. So I said goodbye to them and went on to Macedonia.",
  "korean_text": "내가 내 형제 디도를 만나지 못하므로 내 심령이 편하지 못하여 그들을 작별하고 마게도냐로 갔노라",
  "sentences": [
    {
      "sequence_order": 1,
      "original_text": "I still had no peace of mind",
      "korean_translation": "나는 여전히 마음의 평안이 없었습니다",
      "word_indices": [
        198,
        325
      ]
    },
    {
      "sequence_order": 2,
      "original_text": "because I did not find my brother Titus there",
      "korean_translation": "왜냐하면 그곳에서 내 형제 디도를 찾지 못했기 때문입니다",
      "word_indices": [
        53,
        55
      ]
    },
    {
      "sequence_order": 3,
      "original_text": "So I said goodbye to them",
      "korean_translation": "그래서 나는 그들에게 작별 인사를 하고",
      "word_indices": [
        2546
      ]
    },
    {
      "sequence_order": 4,
      "original_text": "and went on to Macedonia",
      "korean_translation": "마케도니아로 떠났습니다",
      "word_indices": []
    }
  ]
}