{
  "verse_reference": "Hosea 4:2",
  "version": "EASY",
  "original_text": "They curse people, they tell lies, they murder people, they rob people. They are guilty of adultery. They continue to kill more and more people.",
  "korean_text": "오직 저주와 속임과 살인과 도둑질과 간음뿐이요 포악하여 피가 피를 뒤이음이라",
  "sentences": [
    {
      "sequence_order": 1,
      "original_text": "They curse people",
      "korean_translation": "그들은 사람들을 저주합니다",
      "word_indices": [
        373
      ]
    },
    {
      "sequence_order": 2,
      "original_text": "they tell lies",
      "korean_translation": "그들은 거짓말을 합니다",
      "word_indices": []
    },
    {
      "sequence_order": 3,
      "original_text": "they murder people",
      "korean_translation": "그들은 사람들을 살해합니다",
      "word_indices": [
        537
      ]
    },
    {
      "sequence_order": 4,
      "original_text": "they rob people",
      "korean_translation": "그들은 사람들을 약탈합니다",
      "word_indices": []
    },
    {
      "sequence_order": 5,
      "original_text": "They are guilty of adultery",
      "korean_translation": "그들은 간음한 죄가 있습니다",
      "word_indices": [
        232,
        1557
      ]
    },
    {
      "sequence_order": 6,
      "original_text": "They continue to kill more and more people",
      "korean_translation": "그들은 계속해서 점점 더 많은 사람들을 죽입니다",
      "word_indices": [
        26
      ]
    }
  ]
}