{
  "verse_reference": "Isaiah 24:19",
  "version": "KJV",
  "original_text": "The earth is utterly broken down, the earth is clean dissolved, the earth is moved exceedingly.",
  "korean_text": "땅이 깨지고 깨지며 땅이 갈라지고 갈라지며 땅이 흔들리고 흔들리며",
  "sentences": [
    {
      "sequence_order": 1,
      "original_text": "The earth is utterly broken down",
      "korean_translation": "땅이 완전히 부서지고",
      "word_indices": [
        14,
        333
      ]
    },
    {
      "sequence_order": 2,
      "original_text": "earth is clean dissolved",
      "korean_translation": "땅이 깨끗이 녹아내리고",
      "word_indices": [
        244
      ]
    },
    {
      "sequence_order": 3,
      "original_text": "earth is moved exceedingly",
      "korean_translation": "땅이 극심하게 흔들리도다",
      "word_indices": [
        756
      ]
    }
  ]
}