{
  "verse_reference": "Isaiah 58:5",
  "version": "KJV",
  "original_text": "Is it such a fast that I have chosen? a day for a man to afflict his soul? is it to bow down his head as a bulrush, and to spread sackcloth and ashes under him? wilt thou call this a fast, and an acceptable day to the Lord?",
  "korean_text": "이것이 어찌 내가 기뻐하는 금식이 되겠으며 이것이 어찌 사람이 자기의 마음을 괴롭게 하는 날이 되겠느냐 그의 머리를 갈대 같이 숙이고 굵은 베와 재를 펴는 것을 어찌 금식이라 하겠으며 여호와께 열납될 날이라 하겠느냐",
  "sentences": [
    {
      "sequence_order": 1,
      "original_text": "Is it such a fast that I have chosen?",
      "korean_translation": "내가 선택한 금식이 바로 이것인가?",
      "word_indices": [
        276
      ]
    },
    {
      "sequence_order": 2,
      "original_text": "a day for a man to afflict his soul?",
      "korean_translation": "사람이 자신의 영혼을 괴롭히는 날인가?",
      "word_indices": [
        365
      ]
    },
    {
      "sequence_order": 3,
      "original_text": "is it to bow down his head as a bulrush,",
      "korean_translation": "그가 갈대처럼 고개를 숙이는 것인가?",
      "word_indices": [
        14,
        3196
      ]
    },
    {
      "sequence_order": 4,
      "original_text": "and to spread sackcloth and ashes under him?",
      "korean_translation": "그리고 그 아래에 굵은 베옷과 재를 펴는 것인가?",
      "word_indices": [
        290,
        683,
        702
      ]
    },
    {
      "sequence_order": 5,
      "original_text": "wilt thou call this a fast,",
      "korean_translation": "네가 이것을 금식이라 부을 것인가?",
      "word_indices": [
        276
      ]
    },
    {
      "sequence_order": 6,
      "original_text": "and an acceptable day to the Lord?",
      "korean_translation": "그리고 주께 받으실 만한 날이라고 부을 것인가?",
      "word_indices": [
        1136
      ]
    }
  ]
}