{
  "verse_reference": "Zechariah 4:13",
  "version": "KJV",
  "original_text": "And he answered me and said, Knowest thou not what these be? And I said, No, my lord.",
  "korean_text": "그가 내게 대답하여 이르되 네가 이것이 무엇인지 알지 못하느냐 하는지라 내가 대답하되 내 주여 알지 못하나이다 하니",
  "sentences": [
    {
      "sequence_order": 1,
      "original_text": "And he answered me",
      "korean_translation": "그가 내게 대답하여",
      "word_indices": []
    },
    {
      "sequence_order": 2,
      "original_text": "and said",
      "korean_translation": "말하였되",
      "word_indices": []
    },
    {
      "sequence_order": 3,
      "original_text": "Knowest thou not what these be?",
      "korean_translation": "네가 이것들이 무엇인지 알지 못하느냐?",
      "word_indices": []
    },
    {
      "sequence_order": 4,
      "original_text": "And I said",
      "korean_translation": "내가 말하되",
      "word_indices": []
    },
    {
      "sequence_order": 5,
      "original_text": "No, my lord.",
      "korean_translation": "아니요, 나의 주여.",
      "word_indices": []
    }
  ]
}