{
  "verse_reference": "Joshua 19:34",
  "version": "ESV",
  "original_text": "Then the boundary turns westward to Aznoth-tabor and goes from there to Hukkok, touching Zebulun at the south and Asher on the west and Judah on the east at the Jordan.",
  "korean_text": "서쪽으로 돌아 아스놋 다볼에 이르고 그 곳에서부터 훅곡으로 나아가 남쪽은 스불론에 이르고 서쪽은 아셀에 이르며 해 뜨는 쪽은 요단에서 유다에 이르고",
  "sentences": [
    {
      "sequence_order": 1,
      "original_text": "Then the boundary turns westward",
      "korean_translation": "그때 경계는 서쪽으로 향합니다",
      "word_indices": [
        45,
        584,
        1759
      ]
    },
    {
      "sequence_order": 2,
      "original_text": "to Aznoth-tabor",
      "korean_translation": "아스노드다보르로",
      "word_indices": [
        4831
      ]
    },
    {
      "sequence_order": 3,
      "original_text": "and goes from there to Hukkok",
      "korean_translation": "그리고 거기서부터 후콕으로 갑니다",
      "word_indices": []
    },
    {
      "sequence_order": 4,
      "original_text": "touching Zebulun at the south",
      "korean_translation": "남쪽에서 스불론 지역에 닿습니다",
      "word_indices": [
        410
      ]
    },
    {
      "sequence_order": 5,
      "original_text": "and Asher on the west",
      "korean_translation": "서쪽에서 아셀 지역에 닿습니다",
      "word_indices": [
        557
      ]
    },
    {
      "sequence_order": 6,
      "original_text": "and Judah on the east at the Jordan",
      "korean_translation": "요단강 동쪽에서 유다 지역에 닿습니다",
      "word_indices": [
        255
      ]
    }
  ]
}