{
  "verse_reference": "2 Kings 21:10",
  "version": "ESV",
  "original_text": "And the Lord said by his servants the prophets,",
  "korean_text": "여호와께서 그의 종 모든 선지자들을 통하여 말씀하여 이르시되",
  "sentences": [
    {
      "sequence_order": 1,
      "original_text": "And the Lord said",
      "korean_translation": "주께서 말씀하시되",
      "word_indices": []
    },
    {
      "sequence_order": 2,
      "original_text": "by his servants the prophets,",
      "korean_translation": "자기 종 선지자들을 통하여,",
      "word_indices": [
        22,
        71
      ]
    }
  ]
}