{
  "verse_reference": "2 Chronicles 25:6",
  "version": "NIV",
  "original_text": "He also hired a hundred thousand fighting men from Israel for a hundred talents of silver.",
  "korean_text": "또 은 백 달란트로 이스라엘 나라에서 큰 용사 십만 명을 고용하였더니",
  "sentences": [
    {
      "sequence_order": 1,
      "original_text": "He also hired a hundred thousand fighting men",
      "korean_translation": "그는 또한 십만 명의 용병을 고용했습니다",
      "word_indices": [
        28,
        136,
        227
      ]
    },
    {
      "sequence_order": 2,
      "original_text": "from Israel",
      "korean_translation": "이스라엘에서",
      "word_indices": []
    },
    {
      "sequence_order": 3,
      "original_text": "for a hundred talents of silver",
      "korean_translation": "백 달란트의 은으로",
      "word_indices": [
        124,
        952
      ]
    }
  ]
}