{
  "verse_reference": "2 Timothy 2:15",
  "version": "KJV",
  "original_text": "Study to shew thyself approved unto God, a workman that needeth not to be ashamed, rightly dividing the word of truth.",
  "korean_text": "너는 진리의 말씀을 옳게 분별하며 부끄러울 것이 없는 일꾼으로 인정된 자로 자신을 하나님 앞에 드리기를 힘쓰라",
  "sentences": [
    {
      "sequence_order": 1,
      "original_text": "Study to shew thyself approved unto God",
      "korean_translation": "네 자신을 하나님께 인정받도록 힘쓰라",
      "word_indices": [
        146,
        3477
      ]
    },
    {
      "sequence_order": 2,
      "original_text": "a workman that needeth not to be ashamed",
      "korean_translation": "부끄러울 필요가 없는 일꾼으로서",
      "word_indices": [
        1165,
        2378
      ]
    },
    {
      "sequence_order": 3,
      "original_text": "rightly dividing the word of truth",
      "korean_translation": "진리의 말씀을 바르게 나누라",
      "word_indices": [
        2827
      ]
    }
  ]
}