{
  "verse_reference": "Judges 14:9",
  "version": "NIV",
  "original_text": "He scooped out the honey with his hands and ate as he went along. When he rejoined his parents, he gave them some, and they too ate it. But he did not tell them that he had taken the honey from the lion’s carcass.",
  "korean_text": "손으로 그 꿀을 떠서 걸어가며 먹고 그의 부모에게 이르러 그들에게 그것을 드려서 먹게 하였으나 그 꿀을 사자의 몸에서 떠왔다고는 알리지 아니하였더라",
  "sentences": [
    {
      "sequence_order": 1,
      "original_text": "He scooped out the honey with his hands",
      "korean_translation": "그는 손으로 꿀을 퍼냈다",
      "word_indices": [
        9,
        785,
        3485
      ]
    },
    {
      "sequence_order": 2,
      "original_text": "and ate as he went along",
      "korean_translation": "그리고 걸어가면서 먹었다",
      "word_indices": []
    },
    {
      "sequence_order": 3,
      "original_text": "When he rejoined his parents",
      "korean_translation": "그가 부모님에게 다시 합류했을 때",
      "word_indices": [
        755,
        5078
      ]
    },
    {
      "sequence_order": 4,
      "original_text": "he gave them some",
      "korean_translation": "그는 그들에게 약간을 주었다",
      "word_indices": [
        5
      ]
    },
    {
      "sequence_order": 5,
      "original_text": "and they too ate it",
      "korean_translation": "그리고 그들도 그것을 먹었다",
      "word_indices": []
    },
    {
      "sequence_order": 6,
      "original_text": "But he did not tell them",
      "korean_translation": "하지만 그는 그들에게 말하지 않았다",
      "word_indices": [
        15
      ]
    },
    {
      "sequence_order": 7,
      "original_text": "that he had taken the honey",
      "korean_translation": "그가 꿀을 가져왔다는 것을",
      "word_indices": [
        785
      ]
    },
    {
      "sequence_order": 8,
      "original_text": "from the lion's carcass",
      "korean_translation": "사자의 사체에서",
      "word_indices": [
        399
      ]
    }
  ]
}