{
  "verse_reference": "Jude 1:5",
  "version": "ESV",
  "original_text": "Now I want to remind you, although you once fully knew it, that Jesus, who saved a people out of the land of Egypt, afterward destroyed those who did not believe.",
  "korean_text": "너희가 본래 모든 사실을 알고 있으나 내가 너희로 다시 생각나게 하고자 하노라 주께서 백성을 애굽에서 구원하여 내시고 후에 믿지 아니하는 자들을 멸하셨으며",
  "sentences": [
    {
      "sequence_order": 1,
      "original_text": "Now I want to remind you",
      "korean_translation": "이제 내가 너희에게 상기시키고자 하노니",
      "word_indices": [
        486,
        2191
      ]
    },
    {
      "sequence_order": 2,
      "original_text": "although you once fully knew it",
      "korean_translation": "너희가 한번은 온전히 알았으나",
      "word_indices": [
        944,
        1264
      ]
    },
    {
      "sequence_order": 3,
      "original_text": "that Jesus",
      "korean_translation": "예수께서",
      "word_indices": []
    },
    {
      "sequence_order": 4,
      "original_text": "who saved a people out of the land of Egypt",
      "korean_translation": "애굽 땅에서 백성을 구원하시고",
      "word_indices": [
        3,
        8
      ]
    },
    {
      "sequence_order": 5,
      "original_text": "afterward destroyed those who did not believe",
      "korean_translation": "후에 믿지 아니하는 자들을 멸하셨음이라",
      "word_indices": [
        99,
        190,
        652
      ]
    }
  ]
}