{
  "verse_reference": "Exodus 1:11",
  "version": "KJV",
  "original_text": "Therefore they did set over them taskmasters to afflict them with their burdens. And they built for Pharaoh treasure cities, Pithom and Raamses.",
  "korean_text": "감독들을 그들 위에 세우고 그들에게 무거운 짐을 지워 괴롭게 하여 그들에게 바로를 위하여 국고성 비돔과 라암셋을 건축하게 하니라",
  "sentences": [
    {
      "sequence_order": 1,
      "original_text": "Therefore they did set over them taskmasters",
      "korean_translation": "그러므로 그들은 그들 위에 감독관을 세웠다",
      "word_indices": [
        1,
        18,
        2393
      ]
    },
    {
      "sequence_order": 2,
      "original_text": "to afflict them with their burdens",
      "korean_translation": "그들의 짐으로 그들을 괴롭히기 위하여",
      "word_indices": [
        1,
        354,
        365
      ]
    },
    {
      "sequence_order": 3,
      "original_text": "And they built for Pharaoh treasure cities",
      "korean_translation": "그리고 그들은 바로를 위해 보물 도시들을 건설했다",
      "word_indices": [
        12,
        337
      ]
    },
    {
      "sequence_order": 4,
      "original_text": "Pithom and Raamses",
      "korean_translation": "브돔과 라암셋을",
      "word_indices": []
    }
  ]
}