{
  "verse_reference": "Exodus 36:29",
  "version": "KJV",
  "original_text": "And they were coupled beneath, and coupled together at the head thereof, to one ring: thus he did to both of them in both the corners.",
  "korean_text": "아래에서부터 위까지 각기 두 겹 두께로 하여 윗고리에 이르게 하고 두 모퉁이 쪽을 다 그리하며",
  "sentences": [
    {
      "sequence_order": 1,
      "original_text": "And they were coupled beneath",
      "korean_translation": "그것들은 아래에서 연결되었고",
      "word_indices": [
        997
      ]
    },
    {
      "sequence_order": 2,
      "original_text": "and coupled together at the head thereof",
      "korean_translation": "그것들의 머리 부분에서 함께 연결되었습니다",
      "word_indices": [
        24,
        51
      ]
    },
    {
      "sequence_order": 3,
      "original_text": "to one ring",
      "korean_translation": "하나의 고리에",
      "word_indices": [
        550
      ]
    },
    {
      "sequence_order": 4,
      "original_text": "thus he did to both of them",
      "korean_translation": "이와 같이 그는 둘 모두에게 했습니다",
      "word_indices": [
        1
      ]
    },
    {
      "sequence_order": 5,
      "original_text": "in both the corners",
      "korean_translation": "양쪽 구석에서",
      "word_indices": [
        422
      ]
    }
  ]
}