{
  "verse_reference": "Mark 12:3",
  "version": "NIV",
  "original_text": "But they seized him, beat him and sent him away empty-handed.",
  "korean_text": "그들이 종을 잡아 심히 때리고 거저 보내었거늘",
  "sentences": [
    {
      "sequence_order": 1,
      "original_text": "But they seized him",
      "korean_translation": "그러나 그들이 그를 붙잡았으니",
      "word_indices": []
    },
    {
      "sequence_order": 2,
      "original_text": "beat him",
      "korean_translation": "그를 때리고",
      "word_indices": [
        754
      ]
    },
    {
      "sequence_order": 3,
      "original_text": "and sent him away empty-handed",
      "korean_translation": "빈손으로 그를 내보냈더라",
      "word_indices": [
        9,
        34,
        866
      ]
    }
  ]
}