{
  "verse_reference": "Deuteronomy 12:31",
  "version": "ESV",
  "original_text": "You shall not worship the Lord your God in that way, for every abominable thing that the Lord hates they have done for their gods, for they even burn their sons and their daughters in the fire to their gods.",
  "korean_text": "네 하나님 여호와께는 네가 그와 같이 행하지 못할 것이라 그들은 여호와께서 꺼리시며 가증히 여기시는 일을 그들의 신들에게 행하여 심지어 자기들의 자녀를 불살라 그들의 신들에게 드렸느니라",
  "sentences": [
    {
      "sequence_order": 1,
      "original_text": "You shall not worship the Lord your God in that way",
      "korean_translation": "너는 그런 방식으로 주 너의 하나님을 섬기지 말라",
      "word_indices": [
        1,
        271
      ]
    },
    {
      "sequence_order": 2,
      "original_text": "for every abominable thing that the Lord hates",
      "korean_translation": "주께서 미워하시는 모든 가증한 것은",
      "word_indices": [
        1940
      ]
    },
    {
      "sequence_order": 3,
      "original_text": "they have done for their gods",
      "korean_translation": "그들이 그들의 신들을 위해 행하였으니",
      "word_indices": [
        1
      ]
    },
    {
      "sequence_order": 4,
      "original_text": "for they even burn their sons and their daughters",
      "korean_translation": "그들은 심지어 자기 아들딸을 불태워",
      "word_indices": [
        2,
        48,
        58
      ]
    },
    {
      "sequence_order": 5,
      "original_text": "in the fire to their gods",
      "korean_translation": "자기 신들에게 불 속에서 바치느니라",
      "word_indices": [
        1,
        72
      ]
    }
  ]
}