{
  "verse_reference": "James 3:9",
  "version": "ESV",
  "original_text": "With it we bless our Lord and Father, and with it we curse people who are made in the likeness of God.",
  "korean_text": "이것으로 우리가 주 아버지를 찬송하고 또 이것으로 하나님의 형상대로 지음을 받은 사람을 저주하나니",
  "sentences": [
    {
      "sequence_order": 1,
      "original_text": "With it we bless our Lord and Father",
      "korean_translation": "우리는 그것으로 주와 아버지를 축복하고",
      "word_indices": [
        9
      ]
    },
    {
      "sequence_order": 2,
      "original_text": "and with it we curse people",
      "korean_translation": "또한 그것으로 사람들을 저주하며",
      "word_indices": [
        3,
        241
      ]
    },
    {
      "sequence_order": 3,
      "original_text": "who are made in the likeness of God.",
      "korean_translation": "그들은 하나님의 형상대로 지음을 받았습니다.",
      "word_indices": [
        1
      ]
    }
  ]
}