{
  "verse_reference": "Job 34:35",
  "version": "KJV",
  "original_text": "Job hath spoken without knowledge, and his words were without wisdom.",
  "korean_text": "욥이 무식하게 말하니 그의 말이 지혜롭지 못하도다 하리라",
  "sentences": [
    {
      "sequence_order": 1,
      "original_text": "Job hath spoken without knowledge",
      "korean_translation": "욥이 지식 없이 말하였으며",
      "word_indices": [
        64,
        186
      ]
    },
    {
      "sequence_order": 2,
      "original_text": "and his words were without wisdom",
      "korean_translation": "그의 말들은 지혜가 없었다",
      "word_indices": [
        64
      ]
    }
  ]
}