{
  "verse_reference": "Hebrews 3:5",
  "version": "EASY",
  "original_text": "We say that Moses served God well, like a servant in God's house. He took care of all God's people. In this way, Moses showed clearly the message that God would speak later.",
  "korean_text": "또한 모세는 장래에 말할 것을 증언하기 위하여 하나님의 온 집에서 종으로서 신실하였고",
  "sentences": [
    {
      "sequence_order": 1,
      "original_text": "We say that Moses served God well,",
      "korean_translation": "모세가 하나님을 잘 섬겼다고 말합니다.",
      "word_indices": []
    },
    {
      "sequence_order": 2,
      "original_text": "like a servant in God's house.",
      "korean_translation": "하나님의 집에서 종과 같이.",
      "word_indices": [
        44,
        67
      ]
    },
    {
      "sequence_order": 3,
      "original_text": "He took care of all God's people.",
      "korean_translation": "그는 하나님의 모든 백성을 돌보았습니다.",
      "word_indices": []
    },
    {
      "sequence_order": 4,
      "original_text": "In this way,",
      "korean_translation": "이렇게하여,",
      "word_indices": []
    },
    {
      "sequence_order": 5,
      "original_text": "Moses showed clearly the message",
      "korean_translation": "모세는 명확히 메시지를 보여주었습니다",
      "word_indices": [
        21,
        352
      ]
    },
    {
      "sequence_order": 6,
      "original_text": "that God would speak later.",
      "korean_translation": "하나님이 나중에 말씀하실 것을.",
      "word_indices": [
        18
      ]
    }
  ]
}