{
  "verse_reference": "Genesis 13:10",
  "version": "NIV",
  "original_text": "Lot looked around and saw that the whole plain of the Jordan toward Zoar was well watered, like the garden of the Lord, like the land of Egypt. (This was before the Lord destroyed Sodom and Gomorrah.)",
  "korean_text": "이에 롯이 눈을 들어 요단 지역을 바라본즉 소알까지 온 땅에 물이 넉넉하니 여호와께서 소돔과 고모라를 멸하시기 전이었으므로 여호와의 동산 같고 애굽 땅과 같았더라",
  "sentences": [
    {
      "sequence_order": 1,
      "original_text": "Lot looked around",
      "korean_translation": "롯이 주위를 둘러보니",
      "word_indices": [
        51,
        456
      ]
    },
    {
      "sequence_order": 2,
      "original_text": "and saw that",
      "korean_translation": "그리고 보니",
      "word_indices": []
    },
    {
      "sequence_order": 3,
      "original_text": "the whole plain of the Jordan toward Zoar",
      "korean_translation": "소알을 향한 요단의 온 평야가",
      "word_indices": [
        99,
        224,
        908
      ]
    },
    {
      "sequence_order": 4,
      "original_text": "was well watered",
      "korean_translation": "물이 충분했더라",
      "word_indices": [
        46
      ]
    },
    {
      "sequence_order": 5,
      "original_text": "like the garden of the Lord",
      "korean_translation": "여호와의 동산 같았고",
      "word_indices": [
        7,
        745
      ]
    },
    {
      "sequence_order": 6,
      "original_text": "like the land of Egypt",
      "korean_translation": "애굽 땅 같았더라",
      "word_indices": [
        7,
        8
      ]
    },
    {
      "sequence_order": 7,
      "original_text": "This was before the Lord destroyed Sodom and Gomorrah",
      "korean_translation": "이것은 여호와께서 소돔과 고모라를 멸하시기 전이었더라",
      "word_indices": [
        69
      ]
    }
  ]
}