{
  "verse_reference": "2 Chronicles 35:24",
  "version": "EASY",
  "original_text": "So they took him out of the chariot that he was riding in. They put him in his other chariot. Then they took him to Jerusalem and he died there. His people buried him beside his ancestors. All the people of Judah and Jerusalem wept because Josiah had died.",
  "korean_text": "그 부하들이 그를 병거에서 내리게 하고 그의 버금 병거에 태워 예루살렘에 이른 후에 그가 죽으니 그의 조상들의 묘실에 장사되니라 온 유다와 예루살렘 사람들이 요시야를 슬퍼하고",
  "sentences": [
    {
      "sequence_order": 1,
      "original_text": "So they took him out of the chariot",
      "korean_translation": "그래서 그들은 그를 병거에서 내려놓았습니다",
      "word_indices": [
        342
      ]
    },
    {
      "sequence_order": 2,
      "original_text": "that he was riding in",
      "korean_translation": "그가 타고 있던",
      "word_indices": []
    },
    {
      "sequence_order": 3,
      "original_text": "They put him in his other chariot",
      "korean_translation": "그들은 그를 다른 병거에 태웠습니다",
      "word_indices": [
        342
      ]
    },
    {
      "sequence_order": 4,
      "original_text": "Then they took him to Jerusalem",
      "korean_translation": "그리고 그들은 그를 예루살렘으로 데려갔습니다",
      "word_indices": []
    },
    {
      "sequence_order": 5,
      "original_text": "and he died there",
      "korean_translation": "그리고 그는 그곳에서 죽었습니다",
      "word_indices": []
    },
    {
      "sequence_order": 6,
      "original_text": "His people buried him beside his ancestors",
      "korean_translation": "그의 백성들은 그를 조상들 곁에 묻었습니다",
      "word_indices": [
        145,
        343
      ]
    },
    {
      "sequence_order": 7,
      "original_text": "All the people of Judah and Jerusalem wept",
      "korean_translation": "유다와 예루살렘의 모든 백성이 울었습니다",
      "word_indices": []
    },
    {
      "sequence_order": 8,
      "original_text": "because Josiah had died",
      "korean_translation": "요시야가 죽었기 때문입니다",
      "word_indices": []
    }
  ]
}