{
  "verse_reference": "1 Chronicles 25:6",
  "version": "EASY",
  "original_text": "All these musicians were under the authority of their fathers. They used cymbals, harps and lyres to make music to worship the Lord in his temple. The king had authority over Asaph, Jeduthun and Heman.",
  "korean_text": "이들이 다 그들의 아버지의 지휘 아래 제금과 비파와 수금을 잡아 여호와의 전에서 노래하여 하나님의 전을 섬겼으며 아삽과 여두둔과 헤만은 왕의 지휘 아래 있었으니",
  "sentences": [
    {
      "sequence_order": 1,
      "original_text": "All these musicians were under the authority of their fathers",
      "korean_translation": "이 모든 음악가들은 그들의 아버지들의 권위 아래에 있었다",
      "word_indices": [
        37,
        110,
        889
      ]
    },
    {
      "sequence_order": 2,
      "original_text": "They used cymbals, harps and lyres",
      "korean_translation": "그들은 심벌즈, 하프와 리라를 사용했다",
      "word_indices": [
        1004
      ]
    },
    {
      "sequence_order": 3,
      "original_text": "to make music to worship the Lord in his temple",
      "korean_translation": "그의 성전에서 주를 예배하기 위해 음악을 만들었다",
      "word_indices": [
        2,
        49,
        89,
        506
      ]
    },
    {
      "sequence_order": 4,
      "original_text": "The king had authority over Asaph, Jeduthun and Heman",
      "korean_translation": "왕은 아삽, 여두둔과 헤만에 대한 권위를 가졌다",
      "word_indices": [
        3,
        110
      ]
    }
  ]
}