{
  "verse_reference": "1 Chronicles 7:12",
  "version": "EASY",
  "original_text": "Shuppim and Huppim were descendants of Ir. The people called the Hushim were descendants of Aher.",
  "korean_text": "일의 아들은 숩빔과 ?빔이요 아헬의 아들은 후심이더라",
  "sentences": [
    {
      "sequence_order": 1,
      "original_text": "Shuppim and Huppim",
      "korean_translation": "숩빔과 후빔은",
      "word_indices": []
    },
    {
      "sequence_order": 2,
      "original_text": "were descendants of Ir",
      "korean_translation": "이르의 자손이었다",
      "word_indices": [
        75
      ]
    },
    {
      "sequence_order": 3,
      "original_text": "The people called the Hushim",
      "korean_translation": "후심이라 불리는 사람들은",
      "word_indices": [
        47
      ]
    },
    {
      "sequence_order": 4,
      "original_text": "were descendants of Aher",
      "korean_translation": "아헬의 자손이었다",
      "word_indices": [
        75
      ]
    }
  ]
}