{
  "verse_reference": "1 Chronicles 5:16",
  "version": "NIV",
  "original_text": "The Gadites lived in Gilead, in Bashan and its outlying villages, and on all the pasturelands of Sharon as far as they extended.",
  "korean_text": "그들이 바산길르앗과 그 마을과 사론의 모든 들에 거주하여 그 사방 변두리에 다다랐더라",
  "sentences": [
    {
      "sequence_order": 1,
      "original_text": "The Gadites lived in Gilead",
      "korean_translation": "갓 사람들은 길르앗에 살았고",
      "word_indices": []
    },
    {
      "sequence_order": 2,
      "original_text": "in Bashan and its outlying villages",
      "korean_translation": "바산과 그 변경 마을들에 살았으며",
      "word_indices": []
    },
    {
      "sequence_order": 3,
      "original_text": "and on all the pasturelands of Sharon",
      "korean_translation": "그리고 사론의 모든 목초지에",
      "word_indices": [
        901
      ]
    },
    {
      "sequence_order": 4,
      "original_text": "as far as they extended",
      "korean_translation": "그들이 미치는 곳까지 살았더라",
      "word_indices": [
        202,
        878
      ]
    }
  ]
}