{
  "verse_reference": "1 Samuel 21:1",
  "version": "EASY",
  "original_text": "David went to visit Ahimelech the priest. He lived in the town of Nob. Ahimelech shook with fear when he saw David. He asked David, ‘Why are you alone? Why is nobody with you?’ Samuel 20 Samuel 22",
  "korean_text": "다윗이 놉에 가서 제사장 아히멜렉에게 이르니 아히멜렉이 떨며 다윗을 영접하여 그에게 이르되 어찌하여 네가 홀로 있고 함께 하는 자가 아무도 없느냐 하니",
  "sentences": [
    {
      "sequence_order": 1,
      "original_text": "David went to visit Ahimelech the priest.",
      "korean_translation": "다윗은 아히멜렉 제사장을 만나러 갔습니다.",
      "word_indices": [
        32,
        380
      ]
    },
    {
      "sequence_order": 2,
      "original_text": "He lived in the town of Nob.",
      "korean_translation": "그는 놉이라는 마을에 살았습니다.",
      "word_indices": []
    },
    {
      "sequence_order": 3,
      "original_text": "Ahimelech shook with fear when he saw David.",
      "korean_translation": "아히멜렉은 다윗을 보고 두려워 떨었습니다.",
      "word_indices": [
        452
      ]
    },
    {
      "sequence_order": 4,
      "original_text": "He asked David,",
      "korean_translation": "그는 다윗에게 물었습니다,",
      "word_indices": []
    },
    {
      "sequence_order": 5,
      "original_text": "Why are you alone?",
      "korean_translation": "어째서 당신은 혼자 있습니까?",
      "word_indices": []
    },
    {
      "sequence_order": 6,
      "original_text": "Why is nobody with you?",
      "korean_translation": "당신과 함께 있는 사람이 왜 없습니까?",
      "word_indices": []
    }
  ]
}