{
  "verse_reference": "Revelation 4:1",
  "version": "NIV",
  "original_text": "After this I looked, and there before me was a door standing open in heaven. And the voice I had first heard speaking to me like a trumpet said, “Come up here, and I will show you what must take place after this.”",
  "korean_text": "이 일 후에 내가 보니 하늘에 열린 문이 있는데 내가 들은 바 처음에 내게 말하던 나팔 소리 같은 그 음성이 이르되 이리로 올라오라 이 후에 마땅히 일어날 일들을 내가 네게 보이리라 하시더라",
  "sentences": [
    {
      "sequence_order": 1,
      "original_text": "After this I looked",
      "korean_translation": "이후에 내가 보니",
      "word_indices": [
        51
      ]
    },
    {
      "sequence_order": 2,
      "original_text": "and there before me was a door",
      "korean_translation": "내 앞에 한 문이 있었는데",
      "word_indices": [
        415
      ]
    },
    {
      "sequence_order": 3,
      "original_text": "standing open in heaven",
      "korean_translation": "하늘에 열려 서 있더라",
      "word_indices": [
        45,
        57,
        160
      ]
    },
    {
      "sequence_order": 4,
      "original_text": "And the voice I had first heard",
      "korean_translation": "그리고 내가 처음 들었던 그 음성이",
      "word_indices": [
        241
      ]
    },
    {
      "sequence_order": 5,
      "original_text": "speaking to me like a trumpet said",
      "korean_translation": "나팔 소리 같이 내게 말하며 이르되",
      "word_indices": [
        7,
        29,
        453
      ]
    },
    {
      "sequence_order": 6,
      "original_text": "Come up here",
      "korean_translation": "이리 올라오라",
      "word_indices": []
    },
    {
      "sequence_order": 7,
      "original_text": "and I will show you",
      "korean_translation": "그러면 내가 너에게 보이리라",
      "word_indices": [
        128
      ]
    },
    {
      "sequence_order": 8,
      "original_text": "what must take place after this",
      "korean_translation": "이후에 반드시 일어날 모든 것을",
      "word_indices": [
        18
      ]
    }
  ]
}